[
    {"object": {
        "area": "eastern",
        "anum": 0,
        "new_format": true,
        "name": "pick",
        "short_descr": "a small mining pick",
        "description": "A small mining pick made of what appears to be silver lies on the ground.",
        "material": "generic",
        "item_type": "weapon",
        "extra_flags": "antigood",
        "wear_flags": "take wield",
        "values": {
            "weapon_type": "mace",
            "dice_num": 1,
            "dice_size": 9,
            "attack_type": "pierce",
            "flags": null
        },
        "level": 5,
        "weight": 30,
        "cost": 320,
        "condition": 100,
        "extra_description": [],
        "affects": []
    }},
    {"object": {
        "area": "eastern",
        "anum": 1,
        "new_format": true,
        "name": "banded mail",
        "short_descr": "a glowing suit of banded mail",
        "description": "A glowing suit of banded mail lies on the ground.",
        "material": "generic",
        "item_type": "armor",
        "extra_flags": "glow magic",
        "wear_flags": "take body",
        "values": {
            "vs_pierce": 7,
            "vs_bash": 7,
            "vs_slash": 7,
            "vs_magic": 0
        },
        "level": 23,
        "weight": 0,
        "cost": 7300,
        "condition": 100,
        "extra_description": [],
        "affects": [
            {
                "apply": "armor class",
                "level": 23,
                "modifier": -4,
                "bit_type": "object",
                "bits": null
            },
            {
                "apply": "dexterity",
                "level": 23,
                "modifier": 2,
                "bit_type": "object",
                "bits": null
            }
        ]
    }},
    {"object": {
        "area": "eastern",
        "anum": 2,
        "new_format": true,
        "name": "halberd",
        "short_descr": "the halberd",
        "description": "A mighty halberd lies against the wall.",
        "material": "generic",
        "item_type": "weapon",
        "extra_flags": "magic bless",
        "wear_flags": "take wield",
        "values": {
            "weapon_type": "polearm",
            "dice_num": 2,
            "dice_size": 14,
            "attack_type": "cleave",
            "flags": "twohands"
        },
        "level": 29,
        "weight": 160,
        "cost": 1620,
        "condition": 100,
        "extra_description": [],
        "affects": [
            {
                "apply": "damage roll",
                "level": 29,
                "modifier": 2,
                "bit_type": "object",
                "bits": null
            },
            {
                "apply": "hit roll",
                "level": 29,
                "modifier": 2,
                "bit_type": "object",
                "bits": null
            }
        ]
    }},
    {"object": {
        "area": "eastern",
        "anum": 3,
        "new_format": true,
        "name": "amulet",
        "short_descr": "the amulet",
        "description": "A mushroom shaped amulet lies on the ground.",
        "material": "generic",
        "item_type": "jewelry",
        "extra_flags": "magic",
        "wear_flags": "take neck",
        "values": {},
        "level": 5,
        "weight": 20,
        "cost": 550,
        "condition": 100,
        "extra_description": [],
        "affects": [{
            "apply": "constitution",
            "level": 5,
            "modifier": 1,
            "bit_type": "object",
            "bits": null
        }]
    }},
    {"object": {
        "area": "eastern",
        "anum": 5,
        "new_format": true,
        "name": "bone",
        "short_descr": "a large leg bone",
        "description": "A large leg bone rests on the ground.",
        "material": "generic",
        "item_type": "weapon",
        "extra_flags": null,
        "wear_flags": "take wield",
        "values": {
            "weapon_type": "mace",
            "dice_num": 1,
            "dice_size": 4,
            "attack_type": "pound",
            "flags": null
        },
        "level": 0,
        "weight": 50,
        "cost": 140,
        "condition": 100,
        "extra_description": [],
        "affects": []
    }},
    {"object": {
        "area": "eastern",
        "anum": 6,
        "new_format": true,
        "name": "cactus",
        "short_descr": "a small cactus cup",
        "description": "A small cactus cup lies on the ground.",
        "material": "generic",
        "item_type": "drink",
        "extra_flags": null,
        "wear_flags": "take",
        "values": {
            "capacity": 5,
            "filled": 5,
            "liquid": "water",
            "poisoned": false
        },
        "level": 0,
        "weight": 60,
        "cost": 5,
        "condition": 100,
        "extra_description": [],
        "affects": []
    }},
    {"object": {
        "area": "eastern",
        "anum": 7,
        "new_format": true,
        "name": "basket",
        "short_descr": "a small wicker basket",
        "description": "A small wicker basket sits on the ground.",
        "material": "generic",
        "item_type": "container",
        "extra_flags": null,
        "wear_flags": "take",
        "values": {
            "capacity": 100,
            "flags": "closeable closed",
            "key": 0,
            "max_weight": 10,
            "weight_mult": 100
        },
        "level": 0,
        "weight": 20,
        "cost": 20,
        "condition": 100,
        "extra_description": [],
        "affects": []
    }},
    {"object": {
        "area": "eastern",
        "anum": 8,
        "new_format": true,
        "name": "basket",
        "short_descr": "a small wicker basket",
        "description": "A small wicker basket sits on the ground.",
        "material": "generic",
        "item_type": "container",
        "extra_flags": null,
        "wear_flags": "take",
        "values": {
            "capacity": 100,
            "flags": "closeable closed",
            "key": 0,
            "max_weight": 10,
            "weight_mult": 100
        },
        "level": 0,
        "weight": 20,
        "cost": 20,
        "condition": 100,
        "extra_description": [],
        "affects": []
    }},
    {"object": {
        "area": "eastern",
        "anum": 9,
        "new_format": true,
        "name": "basket",
        "short_descr": "a small wicker basket",
        "description": "A small wicker basket sits on the ground.",
        "material": "generic",
        "item_type": "container",
        "extra_flags": null,
        "wear_flags": "take",
        "values": {
            "capacity": 100,
            "flags": "closeable closed",
            "key": 0,
            "max_weight": 10,
            "weight_mult": 100
        },
        "level": 0,
        "weight": 20,
        "cost": 20,
        "condition": 100,
        "extra_description": [],
        "affects": []
    }},
    {"object": {
        "area": "eastern",
        "anum": 10,
        "new_format": true,
        "name": "basket",
        "short_descr": "a small wicker basket",
        "description": "A small wicker basket sits on the ground.",
        "material": "generic",
        "item_type": "container",
        "extra_flags": null,
        "wear_flags": null,
        "values": {
            "capacity": 100,
            "flags": "closeable closed",
            "key": 0,
            "max_weight": 0,
            "weight_mult": 100
        },
        "level": 0,
        "weight": 0,
        "cost": 0,
        "condition": 100,
        "extra_description": [],
        "affects": []
    }},
    {"object": {
        "area": "eastern",
        "anum": 11,
        "new_format": true,
        "name": "rope",
        "short_descr": "a coil of rope",
        "description": "A long coil of rope lies on the ground.",
        "material": "generic",
        "item_type": "furniture",
        "extra_flags": null,
        "wear_flags": "take",
        "values": {
            "max_people": 0,
            "max_weight": 0,
            "flags": null,
            "heal_rate": 100,
            "mana_rate": 100
        },
        "level": 0,
        "weight": 120,
        "cost": 20,
        "condition": 100,
        "extra_description": [],
        "affects": []
    }},
    {"object": {
        "area": "eastern",
        "anum": 12,
        "new_format": true,
        "name": "stakes",
        "short_descr": "a bunch of stakes",
        "description": "A small bundle of stakes lies here.",
        "material": "generic",
        "item_type": "furniture",
        "extra_flags": null,
        "wear_flags": "take",
        "values": {
            "max_people": 0,
            "max_weight": 0,
            "flags": null,
            "heal_rate": 100,
            "mana_rate": 100
        },
        "level": 0,
        "weight": 60,
        "cost": 20,
        "condition": 100,
        "extra_description": [],
        "affects": []
    }},
    {"object": {
        "area": "eastern",
        "anum": 13,
        "new_format": true,
        "name": "map",
        "short_descr": "an old, tattered map",
        "description": "An old, tattered, and much faded map lies here.",
        "material": "generic",
        "item_type": "furniture",
        "extra_flags": null,
        "wear_flags": "take",
        "values": {
            "max_people": 0,
            "max_weight": 0,
            "flags": null,
            "heal_rate": 100,
            "mana_rate": 100
        },
        "level": 0,
        "weight": 10,
        "cost": 5,
        "condition": 100,
        "extra_description": [],
        "affects": []
    }},
    {"object": {
        "area": "eastern",
        "anum": 14,
        "new_format": true,
        "name": "turban",
        "short_descr": "a thick padded turban",
        "description": "A thick padded turban lies here.",
        "material": "generic",
        "item_type": "clothing",
        "extra_flags": "magic nodrop",
        "wear_flags": "take head",
        "values": {},
        "level": 0,
        "weight": 10,
        "cost": 10,
        "condition": 100,
        "extra_description": [],
        "affects": [{
            "apply": "armor class",
            "level": 0,
            "modifier": 1,
            "bit_type": "object",
            "bits": null
        }]
    }},
    {"object": {
        "area": "eastern",
        "anum": 15,
        "new_format": true,
        "name": "coins",
        "short_descr": "a great pile of treasure",
        "description": "A great, gleaming pile of treasure lies at your feet.",
        "material": "generic",
        "item_type": "money",
        "extra_flags": null,
        "wear_flags": "take",
        "values": {
            "silver": 427,
            "gold": 12
        },
        "level": 0,
        "weight": 0,
        "cost": 0,
        "condition": 100,
        "extra_description": [],
        "affects": []
    }},
    {"object": {
        "area": "eastern",
        "anum": 16,
        "new_format": true,
        "name": "sabre",
        "short_descr": "a long, curved sabre",
        "description": "A long, curved sabre stands upright in the ground.",
        "material": "generic",
        "item_type": "weapon",
        "extra_flags": "antineutral",
        "wear_flags": "take wield",
        "values": {
            "weapon_type": "sword",
            "dice_num": 2,
            "dice_size": 8,
            "attack_type": "slash",
            "flags": null
        },
        "level": 16,
        "weight": 70,
        "cost": 1410,
        "condition": 100,
        "extra_description": [],
        "affects": [{
            "apply": "hit roll",
            "level": 16,
            "modifier": 2,
            "bit_type": "object",
            "bits": null
        }]
    }},
    {"object": {
        "area": "eastern",
        "anum": 17,
        "new_format": true,
        "name": "scimitar",
        "short_descr": "a curved scimitar",
        "description": "A curved scimitar lies at your feet.",
        "material": "generic",
        "item_type": "weapon",
        "extra_flags": "antineutral",
        "wear_flags": "take wield",
        "values": {
            "weapon_type": "sword",
            "dice_num": 2,
            "dice_size": 7,
            "attack_type": "slash",
            "flags": null
        },
        "level": 12,
        "weight": 60,
        "cost": 990,
        "condition": 100,
        "extra_description": [],
        "affects": [{
            "apply": "hit roll",
            "level": 12,
            "modifier": 1,
            "bit_type": "object",
            "bits": null
        }]
    }},
    {"object": {
        "area": "eastern",
        "anum": 18,
        "new_format": true,
        "name": "cutlass",
        "short_descr": "a long, pointed cutlass",
        "description": "A long, pointed cutlass lies here.",
        "material": "generic",
        "item_type": "weapon",
        "extra_flags": "antineutral",
        "wear_flags": "take wield",
        "values": {
            "weapon_type": "sword",
            "dice_num": 2,
            "dice_size": 7,
            "attack_type": "slash",
            "flags": null
        },
        "level": 12,
        "weight": 50,
        "cost": 930,
        "condition": 100,
        "extra_description": [],
        "affects": []
    }},
    {"object": {
        "area": "eastern",
        "anum": 19,
        "new_format": true,
        "name": "potion pink",
        "short_descr": "a pink potion",
        "description": "A pink potion stands here.",
        "material": "generic",
        "item_type": "potion",
        "extra_flags": null,
        "wear_flags": "take",
        "values": {
            "level": 25,
            "skill1": "heal",
            "skill2": "remove curse"
        },
        "level": 13,
        "weight": 60,
        "cost": 1220,
        "condition": 100,
        "extra_description": [],
        "affects": []
    }},
    {"object": {
        "area": "eastern",
        "anum": 20,
        "new_format": true,
        "name": "wand platinum",
        "short_descr": "a platinum wand",
        "description": "A platinum wand lies here.",
        "material": "generic",
        "item_type": "wand",
        "extra_flags": "hum",
        "wear_flags": "take hold",
        "values": {
            "level": 30,
            "recharge": 10,
            "charges": 10,
            "skill": "magic missile"
        },
        "level": 2,
        "weight": 80,
        "cost": 990,
        "condition": 100,
        "extra_description": [],
        "affects": []
    }},
    {"object": {
        "area": "eastern",
        "anum": 21,
        "new_format": true,
        "name": "bow energy strange",
        "short_descr": "a strange energy bow",
        "description": "A strange energy bow lies here.",
        "material": "generic",
        "item_type": "weapon",
        "extra_flags": "glow hum magic bless",
        "wear_flags": "take wield",
        "values": {
            "weapon_type": "unknown",
            "dice_num": 4,
            "dice_size": 5,
            "attack_type": "blast",
            "flags": null
        },
        "level": 21,
        "weight": 200,
        "cost": 2600,
        "condition": 100,
        "extra_description": [],
        "affects": []
    }},
    {"object": {
        "area": "eastern",
        "anum": 22,
        "new_format": true,
        "name": "scroll encrypted",
        "short_descr": "an encrypted scroll",
        "description": "An encrypted scroll lies at your feet.",
        "material": "generic",
        "item_type": "scroll",
        "extra_flags": null,
        "wear_flags": "take",
        "values": {
            "level": 22,
            "skill1": "cure blindness",
            "skill2": "remove curse",
            "skill3": "cure poison"
        },
        "level": 11,
        "weight": 70,
        "cost": 1730,
        "condition": 100,
        "extra_description": [],
        "affects": []
    }},
    {"object": {
        "area": "eastern",
        "anum": 23,
        "new_format": true,
        "name": "chest",
        "short_descr": "an iron bound chest",
        "description": "An iron bound chest with a shiny lock sits here.",
        "material": "generic",
        "item_type": "container",
        "extra_flags": null,
        "wear_flags": null,
        "values": {
            "capacity": 200,
            "flags": "closeable closed locked",
            "key": 5024,
            "max_weight": 200,
            "weight_mult": 100
        },
        "level": 0,
        "weight": 0,
        "cost": 0,
        "condition": 100,
        "extra_description": [],
        "affects": []
    }},
    {"object": {
        "area": "eastern",
        "anum": 24,
        "new_format": true,
        "name": "key golden",
        "short_descr": "a golden key",
        "description": "A shiny golden key lies here.",
        "material": "generic",
        "item_type": "key",
        "extra_flags": null,
        "wear_flags": "take",
        "values": {},
        "level": 0,
        "weight": 10,
        "cost": 0,
        "condition": 100,
        "extra_description": [],
        "affects": []
    }},
    {"object": {
        "area": "eastern",
        "anum": 25,
        "new_format": true,
        "name": "bracelet copper",
        "short_descr": "a copper bracelet",
        "description": "A tarnished copper bracelet lies at your feet.",
        "material": "generic",
        "item_type": "jewelry",
        "extra_flags": "magic nodrop",
        "wear_flags": "take wrist",
        "values": {},
        "level": 20,
        "weight": 100,
        "cost": 1300,
        "condition": 100,
        "extra_description": [],
        "affects": [
            {
                "apply": "damage roll",
                "level": 20,
                "modifier": 2,
                "bit_type": "object",
                "bits": null
            },
            {
                "apply": "hp",
                "level": 20,
                "modifier": 10,
                "bit_type": "object",
                "bits": null
            }
        ]
    }},
    {"object": {
        "area": "eastern",
        "anum": 26,
        "new_format": true,
        "name": "gem ruby",
        "short_descr": "a large ruby",
        "description": "A large ruby lies on the ground collecting dust.",
        "material": "generic",
        "item_type": "gem",
        "extra_flags": "magic",
        "wear_flags": "take hold",
        "values": {},
        "level": 0,
        "weight": 1,
        "cost": 5000,
        "condition": 100,
        "extra_description": [],
        "affects": []
    }},
    {"object": {
        "area": "eastern",
        "anum": 27,
        "new_format": true,
        "name": "gem diamond glittering",
        "short_descr": "a glittering diamond",
        "description": "A glittering diamond lies at your feet.",
        "material": "generic",
        "item_type": "gem",
        "extra_flags": "magic",
        "wear_flags": "take hold",
        "values": {},
        "level": 0,
        "weight": 1,
        "cost": 6000,
        "condition": 100,
        "extra_description": [],
        "affects": []
    }},
    {"object": {
        "area": "eastern",
        "anum": 28,
        "new_format": true,
        "name": "gem sapphire",
        "short_descr": "a brilliant sapphire",
        "description": "A brilliant sapphire lies here twinkling.",
        "material": "generic",
        "item_type": "gem",
        "extra_flags": "magic",
        "wear_flags": "take hold",
        "values": {},
        "level": 0,
        "weight": 1,
        "cost": 2000,
        "condition": 100,
        "extra_description": [],
        "affects": []
    }},
    {"object": {
        "area": "eastern",
        "anum": 29,
        "new_format": true,
        "name": "gem lapis",
        "short_descr": "a deep blue lapis lazuli",
        "description": "A deep blue lapis lazuli gem lies here.",
        "material": "generic",
        "item_type": "gem",
        "extra_flags": "magic",
        "wear_flags": "take hold",
        "values": {},
        "level": 0,
        "weight": 1,
        "cost": 800,
        "condition": 100,
        "extra_description": [],
        "affects": []
    }},
    {"object": {
        "area": "eastern",
        "anum": 30,
        "new_format": true,
        "name": "jewel tiger",
        "short_descr": "the tiger jewel",
        "description": "The Tiger Jewel lies here blazing.",
        "material": "generic",
        "item_type": "gem",
        "extra_flags": "bless",
        "wear_flags": "take hold",
        "values": {},
        "level": 5,
        "weight": 1,
        "cost": 550,
        "condition": 100,
        "extra_description": [],
        "affects": [{
            "apply": "dexterity",
            "level": 5,
            "modifier": 1,
            "bit_type": "object",
            "bits": null
        }]
    }},
    {"object": {
        "area": "eastern",
        "anum": 31,
        "new_format": true,
        "name": "jewel red-eyed",
        "short_descr": "the red-eyed jewel",
        "description": "The red-eyed jewel glares at you greedily.",
        "material": "generic",
        "item_type": "gem",
        "extra_flags": null,
        "wear_flags": "take hold",
        "values": {},
        "level": 15,
        "weight": 1,
        "cost": 2600,
        "condition": 100,
        "extra_description": [],
        "affects": [{
            "apply": "intelligence",
            "level": 15,
            "modifier": 2,
            "bit_type": "object",
            "bits": null
        }]
    }},
    {"object": {
        "area": "eastern",
        "anum": 32,
        "new_format": true,
        "name": "gem emerald",
        "short_descr": "a fiery green emerald",
        "description": "A fiery green emerald sits here.",
        "material": "generic",
        "item_type": "warp_stone",
        "extra_flags": "nolocate",
        "wear_flags": "take hold",
        "values": {},
        "level": 0,
        "weight": 1,
        "cost": 4000,
        "condition": 100,
        "extra_description": [],
        "affects": []
    }}
]
